gen_named_pipe/__init__.py
gen_named_pipe/py.typed
gen_named_pipe/conf/gen_named_pipe.cfg
gen_named_pipe/conf/gen_named_pipe.logo
gen_named_pipe/conf/gen_named_pipe_util.cfg
gen_named_pipe/conf/project.yaml
gen_named_pipe/conf/template/posix/np.template
gen_named_pipe/conf/template/posix/np_close.template
gen_named_pipe/conf/template/posix/np_make.template
gen_named_pipe/conf/template/posix/np_open.template
gen_named_pipe/conf/template/posix/np_read.template
gen_named_pipe/conf/template/posix/np_write.template
gen_named_pipe/log/gen_named_pipe.log
gen_named_pipe/pro/__init__.py
gen_named_pipe/pro/read_template.py
gen_named_pipe/pro/write_template.py
usr/local/bin/gen_named_pipe_run.py
gen_named_pipe-1.1.8.dist-info/LICENSE
gen_named_pipe-1.1.8.dist-info/METADATA
gen_named_pipe-1.1.8.dist-info/WHEEL
gen_named_pipe-1.1.8.dist-info/top_level.txt
gen_named_pipe-1.1.8.dist-info/RECORD
